.gitignore
CHANGES.txt
LICENSE.txt
MANIFEST.in
README.md
requirements.txt
setup.cfg
setup.py
docs/Makefile
docs/README.md
docs/conf.py
docs/index.rst
docs/make.bat
docs/_build/doctrees/environment.pickle
docs/_build/doctrees/index.doctree
docs/_build/doctrees/misc/disclaimer.doctree
docs/_build/doctrees/misc/examples.doctree
docs/_build/doctrees/misc/install.doctree
docs/_build/doctrees/misc/license.doctree
docs/_build/doctrees/misc/modules.doctree
docs/_build/html/.buildinfo
docs/_build/html/genindex.html
docs/_build/html/index.html
docs/_build/html/objects.inv
docs/_build/html/py-modindex.html
docs/_build/html/search.html
docs/_build/html/searchindex.js
docs/_build/html/_images/belgium_3680.png
docs/_build/html/_images/belgium_3680_closer.png
docs/_build/html/_images/belgium_6067.png
docs/_build/html/_images/belgium_8305.png
docs/_build/html/_images/belgium_8305_closer.png
docs/_build/html/_modules/index.html
docs/_build/html/_modules/packing.html
docs/_build/html/_modules/plot_packing.html
docs/_build/html/_modules/Packing/packing.html
docs/_build/html/_modules/Packing/plot_packing.html
docs/_build/html/_sources/index.rst.txt
docs/_build/html/_sources/misc/disclaimer.rst.txt
docs/_build/html/_sources/misc/examples.rst.txt
docs/_build/html/_sources/misc/install.rst.txt
docs/_build/html/_sources/misc/license.rst.txt
docs/_build/html/_sources/misc/modules.rst.txt
docs/_build/html/_static/alabaster.css
docs/_build/html/_static/basic.css
docs/_build/html/_static/bootstrap-sphinx.css
docs/_build/html/_static/bootstrap-sphinx.js
docs/_build/html/_static/custom.css
docs/_build/html/_static/dialog-note.png
docs/_build/html/_static/dialog-seealso.png
docs/_build/html/_static/dialog-todo.png
docs/_build/html/_static/dialog-topic.png
docs/_build/html/_static/dialog-warning.png
docs/_build/html/_static/doctools.js
docs/_build/html/_static/documentation_options.js
docs/_build/html/_static/epub.css
docs/_build/html/_static/file.png
docs/_build/html/_static/footerbg.png
football_packing.egg-info/PKG-INFO
football_packing.egg-info/SOURCES.txt
football_packing.egg-info/dependency_links.txt
football_packing.egg-info/not-zip-safe
football_packing.egg-info/requires.txt
football_packing.egg-info/top_level.txt