Metadata-Version: 1.0
Name: football-packing
Version: 0.2
Summary: Calculate the packing rate for a given pass in football (soccer)
Home-page: https://github.com/samirak93/Football-packing
Author: Samira Kumar
Author-email: samirakumarv@gmail.com
License: LICENSE.txt
Keywords: soccer football analytics packing
Platform: UNKNOWN
